bbrio_package_initial/__init__.py
bbrio_package_initial/chi_performance.py
bbrio_package_initial/chi_performance_parsed_table.py
bbrio_package_initial/word_joining.py
bbrio_package_initial-0.0.6.dist-info/LICENSE.txt
bbrio_package_initial-0.0.6.dist-info/METADATA
bbrio_package_initial-0.0.6.dist-info/WHEEL
bbrio_package_initial-0.0.6.dist-info/top_level.txt
bbrio_package_initial-0.0.6.dist-info/RECORD
