Metadata-Version: 2.1
Name: bbrio-package-initial
Version: 0.0.6
Author: Bhargab Ganguli
Author-email: bhargab.ganguli@gmail.com
License: MIT
Classifier: Programming Language :: Python :: 3
Classifier: License :: OSI Approved :: MIT License
Classifier: Operating System :: OS Independent
License-File: LICENSE.txt
Requires-Dist: pandas
Requires-Dist: scipy
